odoo/addons/web_widget_many2many_tags_multi_selection/README.rst
odoo/addons/web_widget_many2many_tags_multi_selection/__init__.py
odoo/addons/web_widget_many2many_tags_multi_selection/__manifest__.py
odoo/addons/web_widget_many2many_tags_multi_selection/i18n/es.po
odoo/addons/web_widget_many2many_tags_multi_selection/i18n/lt.po
odoo/addons/web_widget_many2many_tags_multi_selection/i18n/nl_NL.po
odoo/addons/web_widget_many2many_tags_multi_selection/i18n/pt.po
odoo/addons/web_widget_many2many_tags_multi_selection/i18n/pt_BR.po
odoo/addons/web_widget_many2many_tags_multi_selection/i18n/web_widget_many2many_tags_multi_selection.pot
odoo/addons/web_widget_many2many_tags_multi_selection/i18n/zh_CN.po
odoo/addons/web_widget_many2many_tags_multi_selection/readme/CONFIGURATION.rst
odoo/addons/web_widget_many2many_tags_multi_selection/readme/CONTRIBUTORS.rst
odoo/addons/web_widget_many2many_tags_multi_selection/readme/DESCRIPTION.rst
odoo/addons/web_widget_many2many_tags_multi_selection/static/description/icon.png
odoo/addons/web_widget_many2many_tags_multi_selection/static/description/index.html
odoo/addons/web_widget_many2many_tags_multi_selection/static/src/js/view_form.js
odoo/addons/web_widget_many2many_tags_multi_selection/views/web_widget_many2many_tags_multi_selection.xml
odoo12_addon_web_widget_many2many_tags_multi_selection-12.0.1.0.1.dist-info/METADATA
odoo12_addon_web_widget_many2many_tags_multi_selection-12.0.1.0.1.dist-info/WHEEL
odoo12_addon_web_widget_many2many_tags_multi_selection-12.0.1.0.1.dist-info/top_level.txt
odoo12_addon_web_widget_many2many_tags_multi_selection-12.0.1.0.1.dist-info/RECORD
